OpenBacktest/ObtEngine.py
OpenBacktest/ObtGraph.py
OpenBacktest/ObtUtility.py
OpenBacktest/ObtWallet.py
OpenBacktest/__init__.py
open_backtest-7.0.0.dist-info/LICENSE
open_backtest-7.0.0.dist-info/METADATA
open_backtest-7.0.0.dist-info/WHEEL
open_backtest-7.0.0.dist-info/top_level.txt
open_backtest-7.0.0.dist-info/RECORD
