Metadata-Version: 2.1
Name: open-backtest
Version: 7.0.0
Summary: Open Backtest is a beginner friendly & powerful backtesting engine for crypto trading
Home-page: https://github.com/Shaft-3796/OpenBacktest
Author: Shaft3796
Author-email: sh4ft.me@gmail.com
License: UNKNOWN
Platform: UNKNOWN
Classifier: Programming Language :: Python :: 3
Classifier: License :: OSI Approved :: MIT License
Classifier: Operating System :: OS Independent
Requires-Python: >=3.6
License-File: LICENSE
Requires-Dist: python-binance
Requires-Dist: pandas
Requires-Dist: numpy
Requires-Dist: plotly
Requires-Dist: ta
